[
	{
		"list": "Ora Cortez",
		"email": "metus.eu@aol.org",
		"skills": "Lincoln, Citroën, BMW, Mahindra and Mahindra",
		"_id": 1
	},
	{
		"list": "Oscar Price",
		"email": "cras.vulputate@icloud.org",
		"skills": "Suzuki, General Motors, Skoda, Volvo, Kia Motors, Fiat, Porsche, Daimler",
		"_id": 2
	},
	{
		"list": "Hayes Chase",
		"email": "commodo.tincidunt.nibh@hotmail.ca",
		"skills": "Isuzu, JLR, Volkswagen, Fiat, BMW, Honda, MINI, Toyota",
		"_id": 3
	},
	{
		"list": "Damian Scott",
		"email": "parturient.montes.nascetur@icloud.couk",
		"skills": "Chevrolet",
		"_id": 4
	},
	{
		"list": "Beau Farrell",
		"email": "sem.eget@protonmail.com",
		"skills": "FAW, Honda, Maruti Suzuki, Daihatsu, Audi, Lincoln",
		"_id": 5
	},
	{
		"list": "Clare Whitfield",
		"email": "nullam@google.edu",
		"skills": "Chevrolet, Lincoln, Seat, Audi, Chrysler, Dongfeng Motor, Dodge, Isuzu",
		"_id": 6
	},
	{
		"list": "Uriah Jordan",
		"email": "tellus.justo@hotmail.edu",
		"skills": "Volkswagen, Tata Motors, Porsche, Infiniti, Renault, Suzuki, Smart, Peugeot",
		"_id": 7
	},
	{
		"list": "Garrison Caldwell",
		"email": "praesent.eu.nulla@hotmail.edu",
		"skills": "Seat, Citroën, Kenworth, Cadillac, Honda, Audi, Mahindra and Mahindra",
		"_id": 8
	},
	{
		"list": "Dean Melendez",
		"email": "magna.nec@outlook.edu",
		"skills": "Mercedes-Benz, Toyota, Suzuki, Citroën, Seat, Audi",
		"_id": 9
	},
	{
		"list": "Ariel O'connor",
		"email": "eu.accumsan@outlook.net",
		"skills": "Toyota, Fiat, JLR, Mercedes-Benz, Mahindra and Mahindra, Kenworth, Seat, Mitsubishi Motors",
		"_id": 10
	},
	{
		"list": "Urielle Madden",
		"email": "in.faucibus.orci@hotmail.couk",
		"skills": "Lincoln, Ford",
		"_id": 11
	},
	{
		"list": "Rajah O'connor",
		"email": "consequat.dolor.vitae@aol.com",
		"skills": "Infiniti, Hyundai Motors, Mitsubishi Motors, Isuzu, Lexus",
		"_id": 12
	},
	{
		"list": "Justin Charles",
		"email": "aliquam.tincidunt@aol.edu",
		"skills": "Ford, Hyundai Motors, BMW, Isuzu",
		"_id": 13
	},
	{
		"list": "Danielle Sanford",
		"email": "mauris.sagittis.placerat@icloud.couk",
		"skills": "Seat, Mazda, Daihatsu, Toyota, Subaru, JLR, Lexus",
		"_id": 14
	},
	{
		"list": "Kuame Hyde",
		"email": "vitae@aol.edu",
		"skills": "GMC, Skoda, Citroën, Porsche, Renault, Tata Motors",
		"_id": 15
	},
	{
		"list": "Mohammad Mclean",
		"email": "ultricies.adipiscing@yahoo.edu",
		"skills": "Peugeot, Volkswagen, Citroën, Nissan, Infiniti",
		"_id": 16
	},
	{
		"list": "Shea Morrow",
		"email": "dictum.eu.eleifend@yahoo.com",
		"skills": "Maruti Suzuki, Peugeot, Fiat, Volvo, Hyundai Motors",
		"_id": 17
	},
	{
		"list": "Shelly Camacho",
		"email": "neque.nullam@outlook.edu",
		"skills": "Dodge, Seat, Nissan, Smart, Ferrari, Volkswagen, Ford, RAM Trucks, Jeep",
		"_id": 18
	},
	{
		"list": "Wang Torres",
		"email": "orci.donec.nibh@outlook.couk",
		"skills": "Citroën, Cadillac, Isuzu",
		"_id": 19
	},
	{
		"list": "Peter Martin",
		"email": "odio.phasellus.at@yahoo.com",
		"skills": "Hyundai Motors, Mahindra and Mahindra, Seat, Nissan, Dongfeng Motor, MINI",
		"_id": 20
	},
	{
		"list": "Dorothy Jensen",
		"email": "odio.aliquam.vulputate@icloud.edu",
		"skills": "FAW, Ford, BMW, Toyota, Daimler",
		"_id": 21
	},
	{
		"list": "Aristotle Guy",
		"email": "cubilia.curae.phasellus@yahoo.ca",
		"skills": "Tata Motors, MINI, Seat, Renault, Peugeot, Daihatsu, Maruti Suzuki, Mazda, Chrysler, Audi",
		"_id": 22
	},
	{
		"list": "Keegan Key",
		"email": "velit.dui@outlook.net",
		"skills": "BMW, Hyundai Motors, Mitsubishi Motors, Jeep, Vauxhall, Peugeot, GMC, FAW, Mazda",
		"_id": 23
	},
	{
		"list": "Shelly Holmes",
		"email": "placerat.velit.quisque@google.com",
		"skills": "Maruti Suzuki, Renault, Ford, Mazda",
		"_id": 24
	},
	{
		"list": "Jason Chambers",
		"email": "cursus.integer.mollis@icloud.net",
		"skills": "Smart, Chevrolet, Lincoln, Ford, Skoda, Acura",
		"_id": 25
	},
	{
		"list": "Alden Mcguire",
		"email": "mauris@outlook.edu",
		"skills": "Dodge, Mitsubishi Motors, RAM Trucks, Subaru, Lexus, Buick, Ford",
		"_id": 26
	},
	{
		"list": "Graham Pratt",
		"email": "mi@google.edu",
		"skills": "BMW, Smart, Kia Motors, Audi, RAM Trucks, Subaru, Ferrari, Skoda, JLR, Dodge",
		"_id": 27
	},
	{
		"list": "Timon Yang",
		"email": "a.malesuada.id@hotmail.net",
		"skills": "Lexus, Mahindra and Mahindra, Toyota, Ferrari, BMW, Tata Motors",
		"_id": 28
	},
	{
		"list": "Duncan Kim",
		"email": "sed.pharetra@hotmail.ca",
		"skills": "Smart, Dacia",
		"_id": 29
	},
	{
		"list": "Abraham Jones",
		"email": "magna.sed@outlook.com",
		"skills": "GMC, Vauxhall, Mazda",
		"_id": 30
	},
	{
		"list": "Chloe Richmond",
		"email": "arcu@yahoo.net",
		"skills": "Honda, Mercedes-Benz, Fiat",
		"_id": 31
	},
	{
		"list": "Sophia Miranda",
		"email": "magna.cras@hotmail.couk",
		"skills": "Lexus, Nissan, Dongfeng Motor, Buick, Jeep, Mazda, Dacia",
		"_id": 32
	},
	{
		"list": "Duncan Cameron",
		"email": "mi.lorem@protonmail.couk",
		"skills": "Dongfeng Motor, Mitsubishi Motors, Daihatsu, Mercedes-Benz",
		"_id": 33
	},
	{
		"list": "Pascale Kramer",
		"email": "in.mi.pede@aol.edu",
		"skills": "Skoda, Seat",
		"_id": 34
	},
	{
		"list": "Burke Blake",
		"email": "sed.congue@icloud.com",
		"skills": "Volvo, Buick, Citroën, Lincoln, Skoda, Mahindra and Mahindra, Dongfeng Motor, Mazda, Chevrolet",
		"_id": 35
	},
	{
		"list": "Quamar Stein",
		"email": "vivamus.euismod@outlook.couk",
		"skills": "Kenworth, Toyota, Jeep, General Motors, GMC, Porsche",
		"_id": 36
	},
	{
		"list": "Keaton Garza",
		"email": "et@aol.net",
		"skills": "MINI, Fiat, Buick",
		"_id": 37
	},
	{
		"list": "Kennedy Rodriguez",
		"email": "faucibus.leo.in@aol.net",
		"skills": "Dodge, Audi, Dongfeng Motor",
		"_id": 38
	},
	{
		"list": "Ifeoma Robles",
		"email": "cras.vulputate.velit@google.com",
		"skills": "Audi",
		"_id": 39
	},
	{
		"list": "Alexander Bowman",
		"email": "montes.nascetur@icloud.couk",
		"skills": "Isuzu, Daimler",
		"_id": 40
	},
	{
		"list": "Blythe Rowe",
		"email": "inceptos.hymenaeos.mauris@protonmail.com",
		"skills": "Audi, Isuzu, Cadillac, Mitsubishi Motors, Skoda, Kenworth",
		"_id": 41
	},
	{
		"list": "Penelope Stephens",
		"email": "tellus@yahoo.net",
		"skills": "BMW, Vauxhall, Buick, Seat, Smart, Mazda, Chrysler",
		"_id": 42
	},
	{
		"list": "Moses Lewis",
		"email": "amet@outlook.couk",
		"skills": "Ford, Mahindra and Mahindra, Fiat, Mazda, MINI, Citroën, Dacia, Lincoln",
		"_id": 43
	},
	{
		"list": "Linda Lynn",
		"email": "erat.vivamus@hotmail.edu",
		"skills": "Tata Motors, Smart, Mahindra and Mahindra, Mazda, Mitsubishi Motors, Lexus, Chrysler",
		"_id": 44
	},
	{
		"list": "Lavinia Mccray",
		"email": "rutrum.justo.praesent@outlook.org",
		"skills": "Kia Motors, Infiniti, General Motors, Subaru, Lexus, Suzuki, Nissan, FAW, Porsche, Dongfeng Motor",
		"_id": 45
	},
	{
		"list": "Abel Rosario",
		"email": "duis@google.edu",
		"skills": "Volkswagen, Suzuki, Kia Motors",
		"_id": 46
	},
	{
		"list": "Dorian Jennings",
		"email": "vulputate.mauris.sagittis@icloud.edu",
		"skills": "Mazda, Infiniti, Subaru, Seat",
		"_id": 47
	},
	{
		"list": "Chiquita Oneal",
		"email": "sit@hotmail.couk",
		"skills": "Hyundai Motors, Infiniti, Dongfeng Motor, Daihatsu",
		"_id": 48
	},
	{
		"list": "Raven Pratt",
		"email": "dictum@icloud.couk",
		"skills": "MINI, Mahindra and Mahindra, Mercedes-Benz, Jeep, Audi, Mazda, Volvo, Lexus, Kenworth",
		"_id": 49
	},
	{
		"list": "Sharon Britt",
		"email": "laoreet.posuere@hotmail.org",
		"skills": "Honda, RAM Trucks",
		"_id": 50
	},
	{
		"list": "Daryl Barton",
		"email": "tellus.id.nunc@yahoo.couk",
		"skills": "Fiat, Tata Motors, General Motors, Smart, Porsche, Honda, Dacia, Jeep, BMW",
		"_id": 51
	},
	{
		"list": "Allegra Vaughn",
		"email": "donec.nibh.quisque@icloud.edu",
		"skills": "Lexus, Suzuki, Volkswagen",
		"_id": 52
	},
	{
		"list": "Kristen Hopkins",
		"email": "consequat.lectus@icloud.com",
		"skills": "Lexus, Infiniti, Hyundai Motors, Chevrolet, Mitsubishi Motors, Mahindra and Mahindra, Acura, Buick, Skoda, Renault",
		"_id": 53
	},
	{
		"list": "Lareina Michael",
		"email": "cum.sociis@yahoo.net",
		"skills": "Audi, Mercedes-Benz",
		"_id": 54
	},
	{
		"list": "Lucius Stevenson",
		"email": "turpis.nec@hotmail.edu",
		"skills": "Porsche, Vauxhall, Kenworth, Dodge, Mitsubishi Motors, Skoda, GMC, Nissan, Dongfeng Motor",
		"_id": 55
	},
	{
		"list": "Sean Valdez",
		"email": "quisque.imperdiet.erat@aol.net",
		"skills": "Dacia, Acura, Mazda, Renault, Ferrari, Seat, Chrysler",
		"_id": 56
	},
	{
		"list": "Quyn Oneal",
		"email": "purus.mauris@aol.ca",
		"skills": "Acura, Dacia, Smart, Mahindra and Mahindra, Chrysler, RAM Trucks, Daihatsu, Nissan, Hyundai Motors, Peugeot",
		"_id": 57
	},
	{
		"list": "Joseph Hood",
		"email": "metus.aliquam@protonmail.ca",
		"skills": "Volvo, Kia Motors, Suzuki, Audi",
		"_id": 58
	},
	{
		"list": "Fatima Merrill",
		"email": "ante.iaculis@yahoo.net",
		"skills": "Vauxhall, Mitsubishi Motors, Buick, BMW, Citroën, Mazda, Maruti Suzuki",
		"_id": 59
	},
	{
		"list": "Melvin Daniel",
		"email": "pede@aol.edu",
		"skills": "Maruti Suzuki, Chevrolet, Daimler",
		"_id": 60
	},
	{
		"list": "Lawrence Lang",
		"email": "nunc.sit@aol.ca",
		"skills": "Chrysler, Mercedes-Benz, Infiniti, Mahindra and Mahindra",
		"_id": 61
	},
	{
		"list": "Buckminster Bender",
		"email": "magna.suspendisse.tristique@hotmail.ca",
		"skills": "Dacia, Kia Motors, JLR, Kenworth, Jeep, Ford, Renault, Tata Motors",
		"_id": 62
	},
	{
		"list": "Scott Walters",
		"email": "diam.vel@outlook.edu",
		"skills": "JLR, Ford, Fiat, Lincoln, Smart, Kenworth, Buick, Dacia",
		"_id": 63
	},
	{
		"list": "Hadley Warren",
		"email": "libero.nec.ligula@outlook.com",
		"skills": "Volvo, Audi, Mercedes-Benz, Hyundai Motors, Daimler, Buick, Peugeot, Mitsubishi Motors, Ferrari, JLR",
		"_id": 64
	},
	{
		"list": "Cameran Middleton",
		"email": "nullam.scelerisque@aol.couk",
		"skills": "Ford, Audi, Ferrari, FAW, Daihatsu, Suzuki, Kenworth",
		"_id": 65
	},
	{
		"list": "Haley Sellers",
		"email": "id.magna.et@google.org",
		"skills": "Maruti Suzuki, Isuzu, Ford, Chrysler, Lincoln, Skoda, Kia Motors, Infiniti, FAW, Lexus",
		"_id": 66
	},
	{
		"list": "Salvador Bender",
		"email": "turpis.in.condimentum@protonmail.ca",
		"skills": "Ferrari",
		"_id": 67
	},
	{
		"list": "Barbara Mendoza",
		"email": "dapibus@protonmail.net",
		"skills": "Maruti Suzuki, Porsche, Mercedes-Benz",
		"_id": 68
	},
	{
		"list": "Brian Sullivan",
		"email": "tincidunt.orci@google.com",
		"skills": "Vauxhall, Hyundai Motors",
		"_id": 69
	},
	{
		"list": "Kasper Barker",
		"email": "elit.sed.consequat@aol.com",
		"skills": "Smart, Acura, Suzuki, Mahindra and Mahindra, Nissan, Dongfeng Motor, Kenworth, RAM Trucks, Peugeot",
		"_id": 70
	},
	{
		"list": "Ruby Mathews",
		"email": "magnis.dis@outlook.ca",
		"skills": "General Motors, Toyota, Dacia, Isuzu, Infiniti, Acura",
		"_id": 71
	},
	{
		"list": "Sonia Greene",
		"email": "natoque.penatibus@yahoo.org",
		"skills": "Daihatsu, Mazda, Acura, Lincoln, Honda, Daimler, Dacia, Hyundai Motors, GMC",
		"_id": 72
	},
	{
		"list": "Sophia Silva",
		"email": "aliquam@aol.ca",
		"skills": "Peugeot",
		"_id": 73
	},
	{
		"list": "Ivor Estes",
		"email": "nulla.integer@protonmail.net",
		"skills": "Dacia, Chrysler, Dongfeng Motor, Fiat, Suzuki, Smart, Tata Motors, GMC, Toyota, Infiniti",
		"_id": 74
	},
	{
		"list": "Yasir Townsend",
		"email": "turpis.non@protonmail.org",
		"skills": "Peugeot, Mahindra and Mahindra, Dongfeng Motor, Mercedes-Benz",
		"_id": 75
	},
	{
		"list": "Deanna Patrick",
		"email": "phasellus@google.couk",
		"skills": "Mitsubishi Motors, Lexus, Acura, Isuzu, Mahindra and Mahindra, Daimler, Suzuki, Citroën",
		"_id": 76
	},
	{
		"list": "Ocean Berg",
		"email": "sed.pede.cum@aol.com",
		"skills": "Volkswagen, Isuzu, Fiat, Kenworth, Acura, Vauxhall",
		"_id": 77
	},
	{
		"list": "Jonas Allen",
		"email": "pretium@icloud.ca",
		"skills": "Dongfeng Motor, Vauxhall",
		"_id": 78
	},
	{
		"list": "Alexis Pratt",
		"email": "pede.blandit.congue@protonmail.org",
		"skills": "Toyota, Buick, Mazda, Volvo, GMC, Isuzu, Lincoln",
		"_id": 79
	},
	{
		"list": "Wyoming Bond",
		"email": "adipiscing.enim@outlook.couk",
		"skills": "Isuzu, Hyundai Motors, Jeep",
		"_id": 80
	},
	{
		"list": "Jason Torres",
		"email": "neque.nullam@hotmail.couk",
		"skills": "Toyota, Volvo, Lexus, Maruti Suzuki, Buick, Isuzu, Chrysler, Kenworth",
		"_id": 81
	},
	{
		"list": "Paul Morrison",
		"email": "aliquet.metus@outlook.com",
		"skills": "Skoda",
		"_id": 82
	},
	{
		"list": "Eleanor Burton",
		"email": "vitae@hotmail.com",
		"skills": "Tata Motors, JLR, Jeep, Daimler",
		"_id": 83
	},
	{
		"list": "Morgan Miles",
		"email": "venenatis@icloud.com",
		"skills": "Dacia, Seat, JLR, Mahindra and Mahindra, Porsche, Dongfeng Motor, Daimler",
		"_id": 84
	},
	{
		"list": "Rajah Martin",
		"email": "volutpat.nulla@outlook.net",
		"skills": "Smart, Toyota, Skoda, GMC, Suzuki, Kenworth, General Motors, Lexus, Peugeot, Acura",
		"_id": 85
	},
	{
		"list": "Joan Mcpherson",
		"email": "maecenas.ornare@yahoo.net",
		"skills": "Cadillac, Honda, Tata Motors, Ford",
		"_id": 86
	},
	{
		"list": "Flynn Davenport",
		"email": "laoreet.ipsum@hotmail.couk",
		"skills": "Mitsubishi Motors, Mazda, Chrysler, Vauxhall, Dodge, Lexus, Dongfeng Motor, Infiniti",
		"_id": 87
	},
	{
		"list": "Ronan Lee",
		"email": "sed.neque@hotmail.edu",
		"skills": "Porsche, Volkswagen, Ferrari, Dodge",
		"_id": 88
	},
	{
		"list": "Gillian Gray",
		"email": "morbi.accumsan.laoreet@protonmail.net",
		"skills": "Tata Motors, Vauxhall",
		"_id": 89
	},
	{
		"list": "Oleg Shepard",
		"email": "egestas.ligula@google.net",
		"skills": "Buick, Dodge, Mahindra and Mahindra, Skoda, Volkswagen, Lincoln",
		"_id": 90
	},
	{
		"list": "Warren Kent",
		"email": "est.vitae@protonmail.org",
		"skills": "Smart, Kia Motors, Infiniti, Lexus, MINI, Nissan, Kenworth, Audi, Renault",
		"_id": 91
	},
	{
		"list": "Xenos Mcneil",
		"email": "facilisis.facilisis@google.couk",
		"skills": "Daimler, FAW, MINI, JLR, Acura, Lincoln, Ferrari, Seat, Lexus",
		"_id": 92
	},
	{
		"list": "Joy Banks",
		"email": "venenatis.lacus@hotmail.net",
		"skills": "Seat, Mercedes-Benz, Nissan, GMC",
		"_id": 93
	},
	{
		"list": "Wyatt Johns",
		"email": "blandit@hotmail.net",
		"skills": "Ford, Honda, Chrysler",
		"_id": 94
	},
	{
		"list": "Kameko Torres",
		"email": "egestas.ligula.nullam@google.couk",
		"skills": "Daimler, Mitsubishi Motors, Ferrari, Volvo, Porsche, General Motors, Fiat",
		"_id": 95
	},
	{
		"list": "Lance Payne",
		"email": "ut@hotmail.edu",
		"skills": "Porsche, Lexus, Chrysler, FAW, Volvo, Seat, Maruti Suzuki, Suzuki, Kenworth",
		"_id": 96
	},
	{
		"list": "Edan Carter",
		"email": "nullam.vitae@icloud.ca",
		"skills": "Peugeot, Cadillac, Kenworth, Tata Motors, Chevrolet",
		"_id": 97
	},
	{
		"list": "Rafael Lott",
		"email": "morbi@hotmail.org",
		"skills": "Kia Motors, Ferrari, Maruti Suzuki, Chrysler, JLR, Daimler, Suzuki, Volkswagen",
		"_id": 98
	},
	{
		"list": "Jason Kidd",
		"email": "etiam.ligula@aol.edu",
		"skills": "Hyundai Motors, Buick, Daihatsu, Kenworth, Chrysler",
		"_id": 99
	},
	{
		"list": "Kaitlin Lott",
		"email": "sagittis@icloud.couk",
		"skills": "GMC, Mercedes-Benz, Cadillac, Infiniti, RAM Trucks, Mahindra and Mahindra, Volkswagen",
		"_id": 100
	},
	{
		"list": "Ifeoma Caldwell",
		"email": "a.tortor@icloud.couk",
		"skills": "Acura, Mahindra and Mahindra, Kia Motors, Volvo, Peugeot, RAM Trucks",
		"_id": 101
	},
	{
		"list": "Montana Hart",
		"email": "morbi.tristique@yahoo.couk",
		"skills": "Maruti Suzuki, Hyundai Motors",
		"_id": 102
	},
	{
		"list": "Melodie Mccoy",
		"email": "ut@yahoo.edu",
		"skills": "Suzuki, Kenworth, Buick, Vauxhall, Volkswagen, MINI, Kia Motors, FAW, Honda, Smart",
		"_id": 103
	},
	{
		"list": "Shay Potter",
		"email": "nec.mollis.vitae@outlook.org",
		"skills": "Vauxhall, Porsche, Mercedes-Benz, Cadillac, Acura, Dongfeng Motor, MINI, Chevrolet",
		"_id": 104
	},
	{
		"list": "Shannon Hines",
		"email": "turpis.non@aol.ca",
		"skills": "Infiniti",
		"_id": 105
	},
	{
		"list": "Yoshio Houston",
		"email": "orci@icloud.edu",
		"skills": "Chevrolet, Mahindra and Mahindra, Daihatsu, Peugeot, Seat, Suzuki, Vauxhall, Hyundai Motors, Dodge",
		"_id": 106
	},
	{
		"list": "Mufutau Bowen",
		"email": "varius@protonmail.org",
		"skills": "BMW, Kia Motors, Infiniti, MINI",
		"_id": 107
	},
	{
		"list": "Quynn Brewer",
		"email": "ultrices.iaculis.odio@yahoo.couk",
		"skills": "Acura, Seat",
		"_id": 108
	},
	{
		"list": "Uriah Logan",
		"email": "dictum.ultricies.ligula@google.org",
		"skills": "Renault, Lincoln, Peugeot, Honda, Seat, RAM Trucks, Nissan",
		"_id": 109
	},
	{
		"list": "Joy Reese",
		"email": "augue.scelerisque.mollis@aol.edu",
		"skills": "BMW, Honda, Maruti Suzuki, Jeep, Buick, Daihatsu, Ferrari, Citroën, FAW, Dodge",
		"_id": 110
	},
	{
		"list": "Rashad Bernard",
		"email": "et.nunc.quisque@icloud.com",
		"skills": "General Motors, Smart, JLR, Dacia, GMC",
		"_id": 111
	},
	{
		"list": "Evelyn Montgomery",
		"email": "blandit.nam.nulla@yahoo.edu",
		"skills": "FAW, Smart, Lincoln, General Motors, Cadillac, Dongfeng Motor, Porsche",
		"_id": 112
	},
	{
		"list": "Tamara Campos",
		"email": "fermentum.convallis.ligula@aol.com",
		"skills": "Audi, Volvo, Jeep, JLR, Lincoln, Daihatsu",
		"_id": 113
	},
	{
		"list": "Orson Bender",
		"email": "consequat.nec@aol.com",
		"skills": "Tata Motors, Infiniti, Jeep, Ferrari, Subaru, Mahindra and Mahindra, Toyota",
		"_id": 114
	},
	{
		"list": "Maxine Fuentes",
		"email": "pellentesque@hotmail.org",
		"skills": "Dacia, Ford, Skoda, Jeep, GMC, Acura, Mitsubishi Motors, Renault, Lexus",
		"_id": 115
	},
	{
		"list": "Tate Cole",
		"email": "sem.molestie@google.ca",
		"skills": "Nissan, Acura, Kia Motors, Volkswagen, Skoda, JLR, Cadillac, Infiniti, Maruti Suzuki, General Motors",
		"_id": 116
	},
	{
		"list": "Dylan Cohen",
		"email": "tellus.suspendisse@aol.couk",
		"skills": "Nissan, Audi, Toyota, Chrysler, Citroën, Isuzu",
		"_id": 117
	},
	{
		"list": "Jackson Lee",
		"email": "ac.risus@icloud.com",
		"skills": "Suzuki, Infiniti",
		"_id": 118
	},
	{
		"list": "Howard Reyes",
		"email": "in.cursus.et@protonmail.com",
		"skills": "Fiat, Acura, Dodge, Subaru, BMW, Audi",
		"_id": 119
	},
	{
		"list": "Jorden Santana",
		"email": "nunc.mauris@protonmail.ca",
		"skills": "Suzuki, Ford, Jeep, Lincoln, Cadillac, Daimler, Dodge",
		"_id": 120
	},
	{
		"list": "Wing Dixon",
		"email": "cum@outlook.com",
		"skills": "RAM Trucks, Mercedes-Benz, BMW, Volvo, Ferrari, Vauxhall, Lincoln, Subaru, Renault",
		"_id": 121
	},
	{
		"list": "Emma Barker",
		"email": "donec.luctus@icloud.com",
		"skills": "Isuzu, Skoda, Honda, Lexus, Hyundai Motors, Daimler",
		"_id": 122
	},
	{
		"list": "Jared Parks",
		"email": "enim.sed@aol.couk",
		"skills": "Mitsubishi Motors, Lexus, Toyota, Seat, Chrysler, Mazda",
		"_id": 123
	},
	{
		"list": "Troy Fernandez",
		"email": "nunc.mauris.sapien@yahoo.edu",
		"skills": "Chevrolet, Cadillac, Chrysler",
		"_id": 124
	},
	{
		"list": "Tanner Dejesus",
		"email": "quam.vel@icloud.com",
		"skills": "GMC, Renault, Maruti Suzuki, Porsche, Tata Motors, Nissan, Kia Motors",
		"_id": 125
	},
	{
		"list": "Levi Duncan",
		"email": "in@yahoo.ca",
		"skills": "Ferrari, Renault",
		"_id": 126
	},
	{
		"list": "Owen Padilla",
		"email": "sit.amet@hotmail.org",
		"skills": "Dacia, BMW, Skoda, Smart, Peugeot, Mahindra and Mahindra, General Motors, JLR",
		"_id": 127
	},
	{
		"list": "Erasmus Frederick",
		"email": "diam.duis@aol.com",
		"skills": "Toyota, Skoda, Subaru, Infiniti, GMC, Buick, Suzuki, Chrysler, Ford, Mercedes-Benz",
		"_id": 128
	},
	{
		"list": "Lionel Black",
		"email": "aliquet.vel@yahoo.org",
		"skills": "Lexus, Volkswagen",
		"_id": 129
	},
	{
		"list": "Xena Cooley",
		"email": "elit.pede@hotmail.ca",
		"skills": "Chrysler, Maruti Suzuki, Seat, Infiniti, Chevrolet, RAM Trucks, Citroën",
		"_id": 130
	},
	{
		"list": "Howard Kirkland",
		"email": "aliquam@protonmail.ca",
		"skills": "Kenworth, Jeep, Mahindra and Mahindra, Mazda, Dacia, Suzuki, JLR, Daimler",
		"_id": 131
	},
	{
		"list": "Caesar Elliott",
		"email": "lacinia.sed@aol.ca",
		"skills": "Honda, RAM Trucks, Ford, Kia Motors, Mahindra and Mahindra, FAW",
		"_id": 132
	},
	{
		"list": "Dean Alford",
		"email": "non.massa@aol.net",
		"skills": "Vauxhall",
		"_id": 133
	},
	{
		"list": "Noble Hurst",
		"email": "nisl.maecenas.malesuada@hotmail.com",
		"skills": "Renault, Acura, Daihatsu",
		"_id": 134
	},
	{
		"list": "Anika Valenzuela",
		"email": "tincidunt.donec@outlook.couk",
		"skills": "Dongfeng Motor, General Motors, Nissan, Daihatsu, Chrysler, Fiat, Chevrolet, Ferrari",
		"_id": 135
	},
	{
		"list": "Cheryl Shields",
		"email": "consectetuer.adipiscing@aol.org",
		"skills": "Kenworth, Infiniti, Hyundai Motors, Mahindra and Mahindra",
		"_id": 136
	},
	{
		"list": "Gregory Gutierrez",
		"email": "diam.nunc@outlook.ca",
		"skills": "Mitsubishi Motors, Ford, Cadillac, Mazda, Vauxhall, Daimler, General Motors",
		"_id": 137
	},
	{
		"list": "Lev Harvey",
		"email": "bibendum.sed@outlook.ca",
		"skills": "Mahindra and Mahindra, Daimler, Mitsubishi Motors",
		"_id": 138
	},
	{
		"list": "Doris Rosa",
		"email": "convallis.erat.eget@outlook.couk",
		"skills": "Skoda, Fiat, Buick, Nissan, Citroën, Toyota, Renault, General Motors",
		"_id": 139
	},
	{
		"list": "Liberty Ward",
		"email": "lectus.pede@protonmail.org",
		"skills": "Jeep, Tata Motors, Mazda, Hyundai Motors, General Motors, Fiat, Lincoln",
		"_id": 140
	},
	{
		"list": "Catherine Downs",
		"email": "hendrerit@aol.edu",
		"skills": "FAW, Toyota, Dodge, Mitsubishi Motors, Nissan, JLR, MINI, Tata Motors, Suzuki",
		"_id": 141
	},
	{
		"list": "Rafael Terrell",
		"email": "facilisis.lorem@google.org",
		"skills": "MINI, Mazda, Mitsubishi Motors, Honda, Peugeot, Hyundai Motors, Mahindra and Mahindra, Audi, Chevrolet",
		"_id": 142
	},
	{
		"list": "Hamish Stephenson",
		"email": "vitae.erat@icloud.net",
		"skills": "Mazda, FAW, Hyundai Motors, Volvo, Seat",
		"_id": 143
	},
	{
		"list": "Keely Cotton",
		"email": "mi.aliquam@hotmail.ca",
		"skills": "RAM Trucks, Daimler, Nissan, Isuzu",
		"_id": 144
	},
	{
		"list": "Ima Fletcher",
		"email": "metus.facilisis@icloud.edu",
		"skills": "Subaru, Daimler, Kenworth, Nissan, Fiat, BMW, Dongfeng Motor, Chevrolet",
		"_id": 145
	},
	{
		"list": "Dana Herrera",
		"email": "lobortis.nisi@yahoo.com",
		"skills": "BMW, Cadillac, Mercedes-Benz",
		"_id": 146
	},
	{
		"list": "Bernard Fowler",
		"email": "posuere.vulputate@aol.edu",
		"skills": "Fiat, Lincoln",
		"_id": 147
	},
	{
		"list": "Mia Stein",
		"email": "non.leo.vivamus@icloud.edu",
		"skills": "Fiat, Lincoln, JLR, Porsche",
		"_id": 148
	},
	{
		"list": "Joel Sexton",
		"email": "dis.parturient@hotmail.com",
		"skills": "Hyundai Motors, Isuzu, Subaru, Volvo",
		"_id": 149
	},
	{
		"list": "Xenos Myers",
		"email": "tincidunt.dui@aol.com",
		"skills": "Chevrolet, Chrysler",
		"_id": 150
	},
	{
		"list": "Nevada Spears",
		"email": "massa.non@outlook.org",
		"skills": "Isuzu, GMC, Volvo, Cadillac, Nissan",
		"_id": 151
	},
	{
		"list": "Kessie Mcfadden",
		"email": "penatibus.et@google.ca",
		"skills": "Nissan, Volkswagen, Subaru, Isuzu, Mazda, Kia Motors, Mitsubishi Motors",
		"_id": 152
	},
	{
		"list": "James Whitehead",
		"email": "dictum@aol.net",
		"skills": "Honda, Vauxhall, FAW, Renault, Hyundai Motors, Acura, Peugeot, Jeep, Lincoln, Mercedes-Benz",
		"_id": 153
	},
	{
		"list": "Dylan Garza",
		"email": "ligula.donec@protonmail.com",
		"skills": "BMW, Suzuki, Chevrolet",
		"_id": 154
	},
	{
		"list": "Gareth Baird",
		"email": "purus.nullam.scelerisque@aol.org",
		"skills": "Lexus, FAW, Smart, Volkswagen",
		"_id": 155
	},
	{
		"list": "Abraham Cash",
		"email": "sodales@yahoo.org",
		"skills": "Mahindra and Mahindra, Ferrari, Dodge, Buick, Chrysler, Dongfeng Motor",
		"_id": 156
	},
	{
		"list": "Thane Warner",
		"email": "ac@icloud.net",
		"skills": "Maruti Suzuki, Subaru, BMW, Lexus",
		"_id": 157
	},
	{
		"list": "Brady Carson",
		"email": "ultrices.vivamus@protonmail.ca",
		"skills": "Dacia, Dodge",
		"_id": 158
	},
	{
		"list": "Karina Sharpe",
		"email": "magna.malesuada@google.edu",
		"skills": "Dodge, Dongfeng Motor, FAW",
		"_id": 159
	},
	{
		"list": "Uriah Kent",
		"email": "maecenas.libero@icloud.net",
		"skills": "Maruti Suzuki, BMW, Daihatsu, MINI, Toyota, Chevrolet, Suzuki, Acura, Dacia, Citroën",
		"_id": 160
	},
	{
		"list": "Rinah Castaneda",
		"email": "ipsum@aol.net",
		"skills": "Suzuki, Mercedes-Benz, RAM Trucks, Dacia, Infiniti, Dodge, Jeep, Ferrari, Hyundai Motors",
		"_id": 161
	},
	{
		"list": "Hedwig Cantu",
		"email": "pede.nunc@outlook.ca",
		"skills": "Mazda, Buick, Skoda, Dacia",
		"_id": 162
	},
	{
		"list": "Giacomo Church",
		"email": "eu.lacus@yahoo.com",
		"skills": "Chrysler",
		"_id": 163
	},
	{
		"list": "Sacha Nguyen",
		"email": "convallis@aol.org",
		"skills": "RAM Trucks, Mercedes-Benz, Toyota, Kenworth, Chevrolet, Isuzu, Audi, JLR, Porsche",
		"_id": 164
	},
	{
		"list": "Beverly Hull",
		"email": "neque.sed@hotmail.ca",
		"skills": "Infiniti, Ford, Porsche, Fiat, Tata Motors, Hyundai Motors, Mercedes-Benz",
		"_id": 165
	},
	{
		"list": "Sybill Cortez",
		"email": "sit@yahoo.com",
		"skills": "MINI, Cadillac, Toyota, Ferrari, JLR",
		"_id": 166
	},
	{
		"list": "Lydia Silva",
		"email": "sed@google.ca",
		"skills": "Peugeot, Daihatsu",
		"_id": 167
	},
	{
		"list": "Lacy Palmer",
		"email": "donec@yahoo.ca",
		"skills": "Nissan, BMW, Subaru, Dodge, Renault, Mahindra and Mahindra",
		"_id": 168
	},
	{
		"list": "Craig Harrington",
		"email": "ac@hotmail.edu",
		"skills": "Isuzu, Mitsubishi Motors, Porsche, Smart, Renault, Skoda, Mercedes-Benz",
		"_id": 169
	},
	{
		"list": "Victor Dudley",
		"email": "arcu@hotmail.com",
		"skills": "Mazda, Ferrari, Chevrolet, Suzuki, Chrysler, Mitsubishi Motors, Maruti Suzuki, MINI, Dongfeng Motor, Cadillac",
		"_id": 170
	},
	{
		"list": "Mollie Salazar",
		"email": "auctor@outlook.org",
		"skills": "Kenworth, Toyota",
		"_id": 171
	},
	{
		"list": "Hector Martinez",
		"email": "sem.molestie.sodales@outlook.couk",
		"skills": "Renault",
		"_id": 172
	},
	{
		"list": "Ocean Morse",
		"email": "nullam.suscipit@hotmail.com",
		"skills": "Ford, Chrysler, Mahindra and Mahindra",
		"_id": 173
	},
	{
		"list": "Honorato Mack",
		"email": "donec@protonmail.ca",
		"skills": "Mitsubishi Motors, Skoda, General Motors, Honda, Toyota, Dacia, Ferrari, Infiniti, Dodge",
		"_id": 174
	},
	{
		"list": "Acton Hughes",
		"email": "fusce.mollis@icloud.com",
		"skills": "General Motors, Suzuki, Daihatsu",
		"_id": 175
	},
	{
		"list": "Jesse Russell",
		"email": "ipsum.cursus@protonmail.net",
		"skills": "Renault, Toyota, Kenworth, Daimler, Lexus, Jeep, Infiniti, Seat",
		"_id": 176
	},
	{
		"list": "Tate Carr",
		"email": "aliquet.libero@hotmail.com",
		"skills": "Isuzu, Fiat, Smart, Chevrolet",
		"_id": 177
	},
	{
		"list": "Jerome Banks",
		"email": "iaculis.odio@aol.edu",
		"skills": "Smart, Kia Motors, Dodge, Tata Motors, Ferrari, Mahindra and Mahindra, BMW, Chevrolet, Hyundai Motors",
		"_id": 178
	},
	{
		"list": "Hasad Bryan",
		"email": "non@hotmail.couk",
		"skills": "Chrysler, Mitsubishi Motors, Subaru, FAW, General Motors, BMW, Renault, Dongfeng Motor",
		"_id": 179
	},
	{
		"list": "Palmer Atkinson",
		"email": "duis.ac.arcu@icloud.org",
		"skills": "Volkswagen, Seat, Fiat, Renault, Lincoln, Cadillac, JLR, Peugeot, Skoda",
		"_id": 180
	},
	{
		"list": "Ahmed Haley",
		"email": "ultrices.vivamus@google.ca",
		"skills": "Hyundai Motors, Lincoln, Renault, Porsche, Tata Motors",
		"_id": 181
	},
	{
		"list": "Noble Brady",
		"email": "eget.ipsum@protonmail.net",
		"skills": "Peugeot, Vauxhall, Nissan, Skoda, Daihatsu",
		"_id": 182
	},
	{
		"list": "Odysseus Hooper",
		"email": "quisque.tincidunt@aol.edu",
		"skills": "Ferrari, Maruti Suzuki, Daihatsu, Mercedes-Benz, Subaru, Mahindra and Mahindra, FAW, Suzuki, Dodge",
		"_id": 183
	},
	{
		"list": "Jameson O'donnell",
		"email": "turpis@hotmail.net",
		"skills": "Ferrari, Tata Motors, Skoda, Renault, Seat, Dongfeng Motor, General Motors",
		"_id": 184
	},
	{
		"list": "Zane Skinner",
		"email": "sagittis.semper.nam@google.couk",
		"skills": "Dodge, Kenworth",
		"_id": 185
	},
	{
		"list": "Asher Grant",
		"email": "morbi.non@protonmail.edu",
		"skills": "Chrysler, Dongfeng Motor, Lexus, MINI, Cadillac, Mercedes-Benz, GMC",
		"_id": 186
	},
	{
		"list": "Blake Hester",
		"email": "sociis.natoque@outlook.edu",
		"skills": "Lincoln, Peugeot, Seat, Renault",
		"_id": 187
	},
	{
		"list": "Jessamine Baldwin",
		"email": "dignissim@protonmail.org",
		"skills": "Citroën, Honda, Peugeot, Volvo, Chrysler, GMC, Skoda",
		"_id": 188
	},
	{
		"list": "Jonah Atkins",
		"email": "nec.eleifend@outlook.edu",
		"skills": "Porsche, Fiat, Infiniti, Skoda",
		"_id": 189
	},
	{
		"list": "Garrison Bates",
		"email": "vel.faucibus@outlook.net",
		"skills": "Daimler, Maruti Suzuki, Seat, MINI",
		"_id": 190
	},
	{
		"list": "Aurelia Haley",
		"email": "iaculis.aliquet@icloud.couk",
		"skills": "Ferrari, Daihatsu, Mitsubishi Motors, Mazda, Chevrolet, BMW, Chrysler, Lincoln, Nissan, Jeep",
		"_id": 191
	},
	{
		"list": "Sophia Ball",
		"email": "congue.in.scelerisque@outlook.couk",
		"skills": "Subaru, Renault, Buick, Kenworth, FAW, General Motors, MINI, Isuzu, Citroën, GMC",
		"_id": 192
	},
	{
		"list": "Ezra Stokes",
		"email": "non.nisi.aenean@outlook.org",
		"skills": "Hyundai Motors, General Motors, Peugeot",
		"_id": 193
	},
	{
		"list": "Wylie Douglas",
		"email": "dictum@icloud.ca",
		"skills": "Mitsubishi Motors, Volvo, Skoda, Vauxhall, Jeep, Kenworth, Toyota, Kia Motors",
		"_id": 194
	},
	{
		"list": "Asher Dawson",
		"email": "vel.pede@icloud.edu",
		"skills": "Volkswagen, Kenworth, Renault, MINI, Suzuki, Isuzu, RAM Trucks",
		"_id": 195
	},
	{
		"list": "Kirby Acosta",
		"email": "nec.malesuada@google.couk",
		"skills": "Hyundai Motors",
		"_id": 196
	},
	{
		"list": "Rina Dillon",
		"email": "pellentesque.eget.dictum@outlook.ca",
		"skills": "Suzuki, Audi, Porsche, Volvo, Daihatsu, GMC",
		"_id": 197
	},
	{
		"list": "Megan Casey",
		"email": "ligula.aliquam@aol.com",
		"skills": "Dacia, Peugeot",
		"_id": 198
	},
	{
		"list": "Elmo Hodge",
		"email": "ultrices.posuere@protonmail.net",
		"skills": "Infiniti, Porsche, Hyundai Motors, Tata Motors, JLR, Mazda, Nissan, Ferrari, Honda, Subaru",
		"_id": 199
	},
	{
		"list": "Shelley Luna",
		"email": "enim.nec@icloud.ca",
		"skills": "Tata Motors, Citroën, Smart, Renault, Dacia, MINI",
		"_id": 200
	}
]